<DOMSymbolItem xmlns:xsi="http://www.w3.org/2001/XMLSchema-instance" xmlns="http://ns.adobe.com/xfl/2008/" name="Component Assets/SliderSkins/SliderTrack_skin" itemID="44fdb8c9-000002a6" linkageExportForAS="true" linkageExportInFirstFrame="false" linkageClassName="SliderTrack_skin" sourceFlashFilepath="Applications/Adobe Flash CS4/Common/Configuration/Components/User Interface.fla" sourceLibraryItemHRef="Component Assets/SliderSkins/SliderTrack_skin" sourceLastModified="1168290411" scaleGridLeft="2.25" scaleGridRight="78" scaleGridTop="-1" scaleGridBottom="3.95" lastModified="1168290411">
  <timeline>
    <DOMTimeline name="SliderTrack_skin">
      <layers>
        <DOMLayer name="skin" color="#4FFF4F" current="true" isSelected="true" autoNamed="false">
          <frames>
            <DOMFrame index="0" keyMode="9728">
              <elements>
                <DOMShape>
                  <fills>
                    <FillStyle index="1">
                      <SolidColor color="#AEB2B4"/>
                    </FillStyle>
                    <FillStyle index="2">
                      <SolidColor color="#EBEBEB"/>
                    </FillStyle>
                    <FillStyle index="3">
                      <SolidColor color="#8C9295"/>
                    </FillStyle>
                    <FillStyle index="4">
                      <SolidColor color="#575E62"/>
                    </FillStyle>
                  </fills>
                  <edges>
                    <Edge fillStyle1="4" edges="!20 20|20 0!20 0|1580 0!1580 0|1580 20"/>
                    <Edge fillStyle0="3" fillStyle1="2" edges="!1580 20|1580 40"/>
                    <Edge fillStyle0="3" edges="!1580 40|1600 40!1600 40|1600 20!1600 20|1580 20"/>
                    <Edge fillStyle0="2" fillStyle1="4" edges="!1580 20|20 20"/>
                    <Edge fillStyle0="3" edges="!1560 60|1580 60!1580 60|1580 40"/>
                    <Edge fillStyle0="3" fillStyle1="2" edges="!1580 40|1560 40"/>
                    <Edge fillStyle0="3" fillStyle1="1" edges="!1560 40|1560 60"/>
                    <Edge fillStyle1="1" edges="!1560 60|40 60"/>
                    <Edge fillStyle0="3" fillStyle1="1" edges="!40 60|40 40"/>
                    <Edge fillStyle0="2" fillStyle1="1" edges="!40 40|1560 40"/>
                    <Edge fillStyle1="3" edges="!40 60|20 60!20 60|20 40!20 40|0 40!0 40|0 20!0 20|20 20"/>
                    <Edge fillStyle0="2" fillStyle1="3" edges="!20 20|20 40!20 40|40 40"/>
                  </edges>
                </DOMShape>
              </elements>
            </DOMFrame>
          </frames>
        </DOMLayer>
      </layers>
    </DOMTimeline>
  </timeline>
</DOMSymbolItem>